flipnslide/__init__.py
flipnslide/dataset.py
flipnslide/ingest.py
flipnslide/tiling.py
flipnslide/util.py
flipnslide/viz.py
flipnslide/tests/__init__.py
flipnslide/tests/test_dataset.py
flipnslide/tests/test_ingest.py
flipnslide/tests/test_tiling.py
flipnslide/tests/test_util.py
flipnslide/tests/test_viz.py
flipnslide-0.0.1.dist-info/AUTHORS.md
flipnslide-0.0.1.dist-info/LICENSE
flipnslide-0.0.1.dist-info/METADATA
flipnslide-0.0.1.dist-info/WHEEL
flipnslide-0.0.1.dist-info/top_level.txt
flipnslide-0.0.1.dist-info/RECORD
