Metadata-Version: 2.1
Name: flipnslide
Version: 0.0.1
Summary: A concise Python package to preprocess large scientific images for use with GPUs.
Author-email: Ellianna Abrahams <ellianna@berkeley.edu>
Project-URL: Homepage, https://github.com/elliesch/flipnslide
Project-URL: Issues, https://github.com/elliesch/flipnslide/issues
Classifier: Programming Language :: Python :: 3
Classifier: License :: OSI Approved :: MIT License
Classifier: Operating System :: OS Independent
Classifier: Topic :: Scientific/Engineering :: Image Processing
Requires-Python: >=3.8
License-File: LICENSE
License-File: AUTHORS.md
Requires-Dist: numpy
Requires-Dist: torch
Requires-Dist: flipnslide
Requires-Dist: pandas
Requires-Dist: matplotlib
Requires-Dist: scipy
Requires-Dist: scikit-learn
Requires-Dist: pystac
Requires-Dist: xarray
Requires-Dist: rioxarray
Requires-Dist: geopandas
Requires-Dist: ipykernel
Requires-Dist: torchvision
Requires-Dist: tensorflow
Requires-Dist: planetary-computer
Requires-Dist: rasterio
Requires-Dist: natsort
Requires-Dist: stackstac
Requires-Dist: jupyter-book
